.reuse/dep5
AUTHORS.md
CHANGELOG.md
CITATION.cff
CODE_OF_CONDUCT.md
CONTRIBUTING.md
LICENSE
README.md
codemeta.json
metador_core/__init__.py
metador_core/cli/__init__.py
metador_core/cli/general.py
metador_core/container/__init__.py
metador_core/container/drivers.py
metador_core/container/interface.py
metador_core/container/protocols.py
metador_core/container/provider.py
metador_core/container/utils.py
metador_core/container/wrappers.py
metador_core/harvester/__init__.py
metador_core/harvester/common.py
metador_core/ih5/PATCH_THEORY.md
metador_core/ih5/__init__.py
metador_core/ih5/container.py
metador_core/ih5/manifest.py
metador_core/ih5/overlay.py
metador_core/ih5/record.py
metador_core/ih5/skeleton.py
metador_core/packer/__init__.py
metador_core/packer/example.py
metador_core/packer/types.py
metador_core/packer/utils.py
metador_core/plugin/__init__.py
metador_core/plugin/entrypoints.py
metador_core/plugin/interface.py
metador_core/plugin/metaclass.py
metador_core/plugin/types.py
metador_core/plugin/util.py
metador_core/plugins.py
metador_core/rdf/__init__.py
metador_core/rdf/lib.py
metador_core/rdf/skos.py
metador_core/schema/__init__.py
metador_core/schema/base.py
metador_core/schema/common/__init__.py
metador_core/schema/common/rocrate.py
metador_core/schema/common/schemaorg.py
metador_core/schema/core.py
metador_core/schema/decorators.py
metador_core/schema/encoder.py
metador_core/schema/examples/__init__.py
metador_core/schema/examples/matsci.py
metador_core/schema/inspect.py
metador_core/schema/jsonschema.py
metador_core/schema/ld.py
metador_core/schema/parser.py
metador_core/schema/partial.py
metador_core/schema/pg.py
metador_core/schema/plugins.py
metador_core/schema/types.py
metador_core/util/__init__.py
metador_core/util/diff.py
metador_core/util/enum.py
metador_core/util/hashsums.py
metador_core/util/models.py
metador_core/util/pytest.py
metador_core/util/typing.py
metador_core/widget/__init__.py
metador_core/widget/common.py
metador_core-0.1.1.dist-info/LICENSE
metador_core-0.1.1.dist-info/LICENSES/CC0-1.0.txt
metador_core-0.1.1.dist-info/LICENSES/MIT.txt
metador_core-0.1.1.dist-info/METADATA
metador_core-0.1.1.dist-info/WHEEL
metador_core-0.1.1.dist-info/entry_points.txt
metador_core-0.1.1.dist-info/RECORD
