Metadata-Version: 2.1
Name: metador-core
Version: 0.1.1
Summary: Core of Metador, the metadata-first research data management framework.
Home-page: https://github.com/Materials-Data-Science-and-Informatics/metador-core
License: MIT
Keywords: metadata,rdm,FAIR,framework,python
Author: Anton Pirogov
Author-email: a.pirogov@fz-juelich.de
Maintainer: Anton Pirogov
Maintainer-email: a.pirogov@fz-juelich.de
Requires-Python: >=3.8,<4.0
Classifier: Development Status :: 3 - Alpha
Classifier: Intended Audience :: Developers
Classifier: Intended Audience :: Science/Research
Classifier: License :: OSI Approved :: MIT License
Classifier: Operating System :: POSIX :: Linux
Classifier: Programming Language :: Python :: 3
Classifier: Programming Language :: Python :: 3.8
Classifier: Programming Language :: Python :: 3.9
Classifier: Programming Language :: Python :: 3.10
Classifier: Programming Language :: Python :: 3.11
Classifier: Topic :: Scientific/Engineering
Classifier: Topic :: Software Development :: Libraries :: Application Frameworks
Classifier: Typing :: Typed
Requires-Dist: Flask (>=2.1.3,<3.0.0)
Requires-Dist: Pillow (>=9.1.1,<10.0.0)
Requires-Dist: Pint (>=0.21,<0.22)
Requires-Dist: h5py (>=3.8.0,<4.0.0)
Requires-Dist: importlib-metadata (>=4.11.4,<5.0.0)
Requires-Dist: isodate (>=0.6.1,<0.7.0)
Requires-Dist: overrides (>=7.0.0,<8.0.0)
Requires-Dist: pandas (>=2.0.3,<3.0.0)
Requires-Dist: panel (>=0.14.0,<0.15.0)
Requires-Dist: phantom-types (>=2.1.0,<3.0.0)
Requires-Dist: pydantic (>=1.10.12,<2.0.0)
Requires-Dist: pydantic-yaml (>=1.1.1,<2.0.0)
Requires-Dist: python-magic (>=0.4.25,<0.5.0)
Requires-Dist: rdflib (>=6.2.0,<7.0.0)
Requires-Dist: runtype (>=0.3.5,<0.4.0)
Requires-Dist: simple-parsing (>=0.0.20,<0.0.21)
Requires-Dist: typer[all] (>=0.9.0,<0.10.0)
Requires-Dist: typing-extensions (>=4.6.0,<5.0.0)
Requires-Dist: wrapt (>=1.14.1,<2.0.0)
Project-URL: Documentation, https://github.com/Materials-Data-Science-and-Informatics/metador-core
Project-URL: Repository, https://github.com/Materials-Data-Science-and-Informatics/metador-core
